pysciencemode/__init__.py
pysciencemode/acks.py
pysciencemode/channel.py
pysciencemode/enums.py
pysciencemode/motomed_interface.py
pysciencemode/p24_interface.py
pysciencemode/rehastim2_interface.py
pysciencemode/sciencemode.py
pysciencemode/utils.py
pysciencemode-1.1.5.dist-info/METADATA
pysciencemode-1.1.5.dist-info/WHEEL
pysciencemode-1.1.5.dist-info/licenses/LICENSE
pysciencemode-1.1.5.dist-info/RECORD
