Metadata-Version: 2.4
Name: pysciencemode
Version: 1.1.5
Summary: Python interface to control the Rehastim2 and P24 devices.
Project-URL: Homepage, https://github.com/s2mLab/pyScienceMode
Project-URL: Bug Tracker, https://github.com/s2mLab/pyScienceMode/issues
Author-email: S2M Lab <kevin.co@umontreal.ca>
License: MIT
License-File: LICENSE
Classifier: License :: OSI Approved :: MIT License
Classifier: Operating System :: OS Independent
Classifier: Programming Language :: Python :: 3
Requires-Python: >=3.10
Requires-Dist: colorama
Requires-Dist: crccheck
Requires-Dist: numpy
Requires-Dist: pyserial
